{
	"parent": "item/generated",
	"textures": {
		"layer0": "item/rabbit_hide"
	},
	"overrides": [
		{ "predicate": { "custom_model_data": 10000000 }, "model": "asurvival:item/hide/pig_hide" },
		{ "predicate": { "custom_model_data": 10000001 }, "model": "asurvival:item/hide/bat_hide" },
		{ "predicate": { "custom_model_data": 10000002 }, "model": "asurvival:item/hide/cat_hide" },
		{ "predicate": { "custom_model_data": 10000003 }, "model": "asurvival:item/hide/cow_hide" },
		{ "predicate": { "custom_model_data": 10000004 }, "model": "asurvival:item/hide/donkey_hide" },
		{ "predicate": { "custom_model_data": 10000005 }, "model": "asurvival:item/hide/horse_hide" },
		{ "predicate": { "custom_model_data": 10000006 }, "model": "asurvival:item/hide/llama_hide" },
		{ "predicate": { "custom_model_data": 10000007 }, "model": "asurvival:item/hide/mushroom_hide" },
		{ "predicate": { "custom_model_data": 10000008 }, "model": "asurvival:item/hide/mule_hide" },
		{ "predicate": { "custom_model_data": 10000009 }, "model": "asurvival:item/hide/ocelot_hide" },
		{ "predicate": { "custom_model_data": 10000010 }, "model": "asurvival:item/hide/sheep_hide" },
		{ "predicate": { "custom_model_data": 10000011 }, "model": "asurvival:item/hide/wolf_hide" },
		{ "predicate": { "custom_model_data": 10000012 }, "model": "asurvival:item/hide/polar_bear_hide" }
	]
}